hasanasha/__init__.py
hasanasha-0.1.dist-info/LICENSE.txt
hasanasha-0.1.dist-info/METADATA
hasanasha-0.1.dist-info/WHEEL
hasanasha-0.1.dist-info/top_level.txt
hasanasha-0.1.dist-info/RECORD
