Metadata-Version: 2.1
Name: hasanasha
Version: 0.1
Home-page: https://github.com/MIVI404cyber
Author: MR.MIVI & HASAN
Author-email: 
License: MIT
Classifier: Programming Language :: Python :: 3
Classifier: License :: OSI Approved :: MIT License
Classifier: Operating System :: OS Independent
License-File: LICENSE.txt
